LICENSE
README.md
fastapi_cache/__init__.py
fastapi_cache/coder.py
fastapi_cache/context.py
fastapi_cache/decorator.py
fastapi_cache/key_builder.py
fastapi_cache/py.typed
fastapi_cache/backends/__init__.py
fastapi_cache/backends/redis.py
fastapi_cache/helpers/__init__.py
fastapi_cache/helpers/invariant.py
fastapi_cache/helpers/typing.py
fastapi_cache/types/__init__.py
fastapi_cache/types/backend.py
fastapi_cache/types/protocols.py
fastapi_cache_middleware-0.0.2.dist-info/METADATA
fastapi_cache_middleware-0.0.2.dist-info/WHEEL
fastapi_cache_middleware-0.0.2.dist-info/licenses/LICENSE
fastapi_cache_middleware-0.0.2.dist-info/RECORD
