Metadata-Version: 2.4
Name: fastapi-cache-middleware
Version: 0.0.2
Summary: Cache for FastAPI. An opinionated fork of fastapi-cache library that uses msgspec for json encoding/decoding where possible
Project-URL: Homepage, https://github.com/quannh1195/fastapi-cache-middleware
Project-URL: Repository, https://github.com/quannh1195/fastapi-cache-middleware.git
Project-URL: Documentation, https://github.com/quannh1195/fastapi-cache-middleware
Author-email: long2ice <long2ice@gmail.com>
License-Expression: Apache-2.0
License-File: LICENSE
Keywords: cache,caching,fastapi
Requires-Python: >=3.12
Requires-Dist: fastapi
Requires-Dist: msgspec<1,>=0
Requires-Dist: pydantic<3,>=2.5.2
Provides-Extra: all
Requires-Dist: aiobotocore<3,>=2.13.1; extra == 'all'
Requires-Dist: aiomcache<1,>=0; extra == 'all'
Requires-Dist: redis<7,>=5; extra == 'all'
Provides-Extra: dynamodb
Requires-Dist: aiobotocore<3,>=2.13.1; extra == 'dynamodb'
Provides-Extra: memcache
Requires-Dist: aiomcache<1,>=0; extra == 'memcache'
Provides-Extra: redis
Requires-Dist: redis<7,>=5; extra == 'redis'
